[
{
  "ra": 143.611,
  "dec": -59.2297,
  "apparent_magnitude": 6.65032,
  "absolute_magnitude": -4.76609,
  "distance": 1919.92,
  "x": 1444.48,
  "y": -772.285,
  "z": -1001.57,
  "temperature": 7899.98,
  "color": 16316415
},
{
  "ra": 130.567,
  "dec": -48.0991,
  "apparent_magnitude": 6.59608,
  "absolute_magnitude": -4.63648,
  "distance": 1764.06,
  "x": 1654.11,
  "y": -599.16,
  "z": 129.668,
  "temperature": 19819.9,
  "color": 13230847
},
{
  "ra": 130.305,
  "dec": -47.3171,
  "apparent_magnitude": 6.92296,
  "absolute_magnitude": -4.55601,
  "distance": 1976.04,
  "x": 1816.34,
  "y": -486.325,
  "z": -607.573,
  "temperature": 7890.94,
  "color": 16316415
},
{
  "ra": 269.739,
  "dec": -22.5176,
  "apparent_magnitude": 6.3608,
  "absolute_magnitude": -3.69028,
  "distance": 1023.8,
  "x": 742.187,
  "y": -699.932,
  "z": -86.1661,
  "temperature": 6677.9,
  "color": 16774373
},
{
  "ra": 269.86,
  "dec": -22.4669,
  "apparent_magnitude": 6.86222,
  "absolute_magnitude": -3.22821,
  "distance": 1042.52,
  "x": 641.664,
  "y": -810.729,
  "z": -133.557,
  "temperature": 19890.4,
  "color": 13230847
},
{
  "ra": 241.315,
  "dec": -56.3399,
  "apparent_magnitude": 6.17318,
  "absolute_magnitude": -4.20393,
  "distance": 1189.66,
  "x": 889.083,
  "y": -595.128,
  "z": -520.237,
  "temperature": 3784.44,
  "color": 16764015
},
{
  "ra": 339.115,
  "dec": 58.4261,
  "apparent_magnitude": 6.17151,
  "absolute_magnitude": -11.5547,
  "distance": 35095.4,
  "x": -9031.67,
  "y": 753.379,
  "z": 33905,
  "temperature": 4871.35,
  "color": 16764015
},
{
  "ra": 273.804,
  "dec": -20.388,
  "apparent_magnitude": 6.01316,
  "absolute_magnitude": -10.0662,
  "distance": 16439.1,
  "x": 1320.4,
  "y": -1415.69,
  "z": -16324.7,
  "temperature": 21691.1,
  "color": 13230847
},
{
  "ra": 102.719,
  "dec": -0.0731912,
  "apparent_magnitude": 6.70107,
  "absolute_magnitude": -6.82735,
  "distance": 5077.9,
  "x": -2196.01,
  "y": 4405.74,
  "z": -1245.84,
  "temperature": 3679.72,
  "color": 16738874
},
{
  "ra": 338.8,
  "dec": 14.6105,
  "apparent_magnitude": 6.68002,
  "absolute_magnitude": -6.61946,
  "distance": 4569.8,
  "x": -613.436,
  "y": 94.1429,
  "z": 4527.46,
  "temperature": 5208.01,
  "color": 16776144
},
{
  "ra": 337.545,
  "dec": 57.0008,
  "apparent_magnitude": 6.95103,
  "absolute_magnitude": -6.76153,
  "distance": 5527.28,
  "x": 1036.03,
  "y": -5276.86,
  "z": 1277.61,
  "temperature": 3722.13,
  "color": 16764015
},
{
  "ra": 333.289,
  "dec": 53.6239,
  "apparent_magnitude": 6.93637,
  "absolute_magnitude": -5.77864,
  "distance": 3491.43,
  "x": -2076.92,
  "y": -2288.23,
  "z": -1624.95,
  "temperature": 3685.42,
  "color": 16738874
},
{
  "ra": 116.291,
  "dec": -24.6527,
  "apparent_magnitude": 6.65425,
  "absolute_magnitude": -5.17908,
  "distance": 2326.31,
  "x": -1598.06,
  "y": -1355.09,
  "z": 1010.75,
  "temperature": 8915.46,
  "color": 16316415
},
{
  "ra": 115.261,
  "dec": -31.6831,
  "apparent_magnitude": 6.60549,
  "absolute_magnitude": -5.3806,
  "distance": 2495.85,
  "x": -234.014,
  "y": 1789.76,
  "z": -1723.73,
  "temperature": 3734.59,
  "color": 16764015
},
{
  "ra": 332.16,
  "dec": 59.5504,
  "apparent_magnitude": 5.96005,
  "absolute_magnitude": -5.20692,
  "distance": 1711.57,
  "x": -652.888,
  "y": 1565.58,
  "z": -228.432,
  "temperature": 4546.51,
  "color": 16764015
},
{
  "ra": 107.794,
  "dec": -4.7033,
  "apparent_magnitude": 6.88406,
  "absolute_magnitude": -5.89621,
  "distance": 3597.94,
  "x": 1748.21,
  "y": -1207.75,
  "z": 2903.49,
  "temperature": 8442.75,
  "color": 16316415
},
{
  "ra": 156.566,
  "dec": -54.5215,
  "apparent_magnitude": 6.33009,
  "absolute_magnitude": -5.64665,
  "distance": 2485.13,
  "x": 416.351,
  "y": -419.087,
  "z": 2413.89,
  "temperature": 3712.74,
  "color": 16764015
},
{
  "ra": 118.917,
  "dec": -28.6485,
  "apparent_magnitude": 4.76736,
  "absolute_magnitude": -5.63865,
  "distance": 1205.59,
  "x": -1070.52,
  "y": 236.392,
  "z": 501.556,
  "temperature": 3637.48,
  "color": 16738874
},
{
  "ra": 202.229,
  "dec": -62.1023,
  "apparent_magnitude": 6.14789,
  "absolute_magnitude": -6.41416,
  "distance": 3253.94,
  "x": 2723.34,
  "y": 1057.87,
  "z": 1432.64,
  "temperature": 8199.93,
  "color": 16316415
},
{
  "ra": 162.307,
  "dec": -60.1842,
  "apparent_magnitude": 6.62099,
  "absolute_magnitude": -4.29249,
  "distance": 1522.99,
  "x": 387.101,
  "y": 1258.6,
  "z": 765.237,
  "temperature": 15107.2,
  "color": 13230847
},
{
  "ra": 264.042,
  "dec": -33.4946,
  "apparent_magnitude": 6.86548,
  "absolute_magnitude": -6.02253,
  "distance": 3780.96,
  "x": 249.057,
  "y": -1407.08,
  "z": -3500.53,
  "temperature": 4618.49,
  "color": 16764015
},
{
  "ra": 15.1373,
  "dec": 63.0288,
  "apparent_magnitude": 5.07406,
  "absolute_magnitude": -4.47491,
  "distance": 812.445,
  "x": -690.336,
  "y": 396.918,
  "z": -161.12,
  "temperature": 7869.96,
  "color": 16316415
},
{
  "ra": 109.758,
  "dec": -19.2803,
  "apparent_magnitude": 5.31349,
  "absolute_magnitude": -6.41722,
  "distance": 2218.93,
  "x": -816.11,
  "y": -662.714,
  "z": -1954.07,
  "temperature": 7867.96,
  "color": 16316415
},
{
  "ra": 112.966,
  "dec": -22.7011,
  "apparent_magnitude": 6.91936,
  "absolute_magnitude": -3.89008,
  "distance": 1451.74,
  "x": -342.284,
  "y": -902.385,
  "z": 1084.48,
  "temperature": 4807.06,
  "color": 16764015
},
{
  "ra": 345.522,
  "dec": 59.8184,
  "apparent_magnitude": 6.70809,
  "absolute_magnitude": -4.50133,
  "distance": 1745.36,
  "x": -888.256,
  "y": -1038.03,
  "z": -1086.17,
  "temperature": 4291.66,
  "color": 16764015
},
{
  "ra": 187.38,
  "dec": -66.8605,
  "apparent_magnitude": 6.24581,
  "absolute_magnitude": -4.91342,
  "distance": 1705.48,
  "x": 1027.93,
  "y": 330.598,
  "z": 1320.12,
  "temperature": 6651,
  "color": 16774373
},
{
  "ra": 5.35116,
  "dec": 59.9531,
  "apparent_magnitude": 6.95311,
  "absolute_magnitude": -4.18557,
  "distance": 1689.41,
  "x": 247.149,
  "y": 865.91,
  "z": -1429.42,
  "temperature": 3834.41,
  "color": 16764015
},
{
  "ra": 168.81,
  "dec": -60.1646,
  "apparent_magnitude": 5.02411,
  "absolute_magnitude": -4.34712,
  "distance": 748.593,
  "x": 195.262,
  "y": 557.789,
  "z": 459.495,
  "temperature": 22712.3,
  "color": 13230847
},
{
  "ra": 184.974,
  "dec": -62.8542,
  "apparent_magnitude": 4.76692,
  "absolute_magnitude": -5.33261,
  "distance": 1046.9,
  "x": -636.726,
  "y": -219.582,
  "z": -801.474,
  "temperature": 7678.69,
  "color": 16316415
},
{
  "ra": 36.6958,
  "dec": 58.8759,
  "apparent_magnitude": 6.59233,
  "absolute_magnitude": -4.17337,
  "distance": 1422.78,
  "x": 820.462,
  "y": 304.214,
  "z": 1121.88,
  "temperature": 17327.8,
  "color": 13230847
},
{
  "ra": 313.958,
  "dec": 47.4176,
  "apparent_magnitude": 4.71372,
  "absolute_magnitude": -6.50466,
  "distance": 1752.57,
  "x": -628.518,
  "y": -690.302,
  "z": -1483.22,
  "temperature": 15024.6,
  "color": 13230847
},
{
  "ra": 14.6118,
  "dec": 63.7136,
  "apparent_magnitude": 6.55576,
  "absolute_magnitude": -4.49286,
  "distance": 1620.78,
  "x": 1024.56,
  "y": 264.179,
  "z": 1227.77,
  "temperature": 16059,
  "color": 13230847
},
{
  "ra": 172.274,
  "dec": -56.6442,
  "apparent_magnitude": 6.41006,
  "absolute_magnitude": -3.7686,
  "distance": 1085.75,
  "x": -446.582,
  "y": 68.4517,
  "z": -987.288,
  "temperature": 30746.2,
  "color": 10539007
},
{
  "ra": 33.7771,
  "dec": 56.9265,
  "apparent_magnitude": 5.11222,
  "absolute_magnitude": -3.49885,
  "distance": 527.491,
  "x": 87.387,
  "y": 482.534,
  "z": 194.349,
  "temperature": 17996.4,
  "color": 13230847
},
{
  "ra": 172.313,
  "dec": -63.5539,
  "apparent_magnitude": 6.26742,
  "absolute_magnitude": -5.667,
  "distance": 2437.16,
  "x": 78.0311,
  "y": -312.668,
  "z": -2415.76,
  "temperature": 6941.35,
  "color": 16774373
},
{
  "ra": 34.722,
  "dec": 57.4213,
  "apparent_magnitude": 6.76407,
  "absolute_magnitude": -4.60367,
  "distance": 1877.36,
  "x": 169.323,
  "y": -1445.43,
  "z": 1185.98,
  "temperature": 3638.37,
  "color": 16738874
},
{
  "ra": 247.597,
  "dec": -37.9726,
  "apparent_magnitude": 6.41838,
  "absolute_magnitude": -4.38024,
  "distance": 1444.52,
  "x": -231.435,
  "y": 153.817,
  "z": -1417.54,
  "temperature": 17792.5,
  "color": 13230847
},
{
  "ra": 105.164,
  "dec": -9.20296,
  "apparent_magnitude": 6.54379,
  "absolute_magnitude": -5.56942,
  "distance": 2646.32,
  "x": 1958.4,
  "y": 1227.82,
  "z": -1288.46,
  "temperature": 6968.23,
  "color": 16774373
},
{
  "ra": 197.39,
  "dec": -62.871,
  "apparent_magnitude": 6.24793,
  "absolute_magnitude": -3.55764,
  "distance": 914.353,
  "x": -355.455,
  "y": 63.5002,
  "z": -840.037,
  "temperature": 6335.87,
  "color": 16774373
},
{
  "ra": 29.962,
  "dec": 59.1608,
  "apparent_magnitude": 6.36758,
  "absolute_magnitude": -4.93709,
  "distance": 1823.62,
  "x": 1524.42,
  "y": 882.716,
  "z": 471.734,
  "temperature": 4535.5,
  "color": 16764015
},
{
  "ra": 39.6059,
  "dec": 57.0462,
  "apparent_magnitude": 5.32147,
  "absolute_magnitude": -5.40984,
  "distance": 1400.43,
  "x": 1072.67,
  "y": 806.901,
  "z": 399.362,
  "temperature": 3730.5,
  "color": 16764015
},
{
  "ra": 154.291,
  "dec": -55.9225,
  "apparent_magnitude": 6.64629,
  "absolute_magnitude": -4.81602,
  "distance": 1960.93,
  "x": -46.7866,
  "y": -1848.06,
  "z": 654.002,
  "temperature": 3704.85,
  "color": 16764015
},
{
  "ra": 153.019,
  "dec": -49.7483,
  "apparent_magnitude": 6.50832,
  "absolute_magnitude": -3.04449,
  "distance": 813.885,
  "x": 516.381,
  "y": 459.821,
  "z": 429.33,
  "temperature": 4199.62,
  "color": 16764015
},
{
  "ra": 162.365,
  "dec": -60.2947,
  "apparent_magnitude": 6.17716,
  "absolute_magnitude": -3.90623,
  "distance": 1039.15,
  "x": 708.981,
  "y": 460.326,
  "z": 604.381,
  "temperature": 6052.01,
  "color": 16774373
},
{
  "ra": 35.1208,
  "dec": 56.9931,
  "apparent_magnitude": 6.6333,
  "absolute_magnitude": -5.19633,
  "distance": 2322.34,
  "x": -18.1121,
  "y": -2307.49,
  "z": 261.628,
  "temperature": 3681.45,
  "color": 16738874
},
{
  "ra": 34.7685,
  "dec": 57.1355,
  "apparent_magnitude": 5.75351,
  "absolute_magnitude": -5.36155,
  "distance": 1671.14,
  "x": -105.96,
  "y": -1581.38,
  "z": 529.824,
  "temperature": 16526.1,
  "color": 13230847
},
{
  "ra": 162.23,
  "dec": -59.4468,
  "apparent_magnitude": 6.99767,
  "absolute_magnitude": -4.21413,
  "distance": 1747.27,
  "x": 823.508,
  "y": 833.61,
  "z": -1296.1,
  "temperature": 17074.6,
  "color": 13230847
},
{
  "ra": 134.37,
  "dec": -50.7495,
  "apparent_magnitude": 6.55222,
  "absolute_magnitude": -4.74393,
  "distance": 1816.48,
  "x": 265.031,
  "y": 132.25,
  "z": -1792.16,
  "temperature": 22928.9,
  "color": 13230847
},
{
  "ra": 326.57,
  "dec": 53.0095,
  "apparent_magnitude": 6.94688,
  "absolute_magnitude": -2.85111,
  "distance": 911.164,
  "x": -275.496,
  "y": -859.574,
  "z": 124.32,
  "temperature": 4843.57,
  "color": 16764015
},
{
  "ra": 112.532,
  "dec": -9.38813,
  "apparent_magnitude": 6.21054,
  "absolute_magnitude": -3.39804,
  "distance": 835.059,
  "x": -123.127,
  "y": 18.7052,
  "z": -825.719,
  "temperature": 3403.29,
  "color": 16738874
},
{
  "ra": 193.422,
  "dec": -60.3494,
  "apparent_magnitude": 5.42141,
  "absolute_magnitude": -5.60636,
  "distance": 1605.29,
  "x": 1398.3,
  "y": 512.921,
  "z": 598.853,
  "temperature": 3670.54,
  "color": 16738874
},
{
  "ra": 163.042,
  "dec": -59.9552,
  "apparent_magnitude": 6.18127,
  "absolute_magnitude": -2.67729,
  "distance": 591.168,
  "x": -204.859,
  "y": -524.493,
  "z": -180.057,
  "temperature": 21237.6,
  "color": 13230847
},
{
  "ra": 304.345,
  "dec": 38.2357,
  "apparent_magnitude": 4.08459,
  "absolute_magnitude": -4.80085,
  "distance": 598.532,
  "x": 56.4056,
  "y": -477.898,
  "z": 355.911,
  "temperature": 18202.6,
  "color": 13230847
},
{
  "ra": 265.985,
  "dec": -6.26912,
  "apparent_magnitude": 6.84045,
  "absolute_magnitude": -3.57037,
  "distance": 1208.27,
  "x": 700.53,
  "y": 678.262,
  "z": -713.54,
  "temperature": 7749.31,
  "color": 16316415
},
{
  "ra": 166.192,
  "dec": -43.6828,
  "apparent_magnitude": 6.49194,
  "absolute_magnitude": -2.36701,
  "distance": 591.276,
  "x": -164.842,
  "y": -555.69,
  "z": -116.803,
  "temperature": 4984.07,
  "color": 16764015
},
{
  "ra": 160.669,
  "dec": -59.2157,
  "apparent_magnitude": 6.58551,
  "absolute_magnitude": -6.361,
  "distance": 3884.2,
  "x": 3467.22,
  "y": -363.501,
  "z": -1712.69,
  "temperature": 15104.5,
  "color": 13230847
},
{
  "ra": 285.115,
  "dec": 56.5253,
  "apparent_magnitude": 6.846,
  "absolute_magnitude": -2.87911,
  "distance": 881.094,
  "x": 252.62,
  "y": 289.033,
  "z": -793.076,
  "temperature": 19279.5,
  "color": 13230847
},
{
  "ra": 269.54,
  "dec": -28.1417,
  "apparent_magnitude": 6.84677,
  "absolute_magnitude": -3.21324,
  "distance": 1028.02,
  "x": 86.4321,
  "y": 62.9982,
  "z": -1022.44,
  "temperature": 23714.3,
  "color": 13230847
},
{
  "ra": 68.5653,
  "dec": 34.3847,
  "apparent_magnitude": 5.4613,
  "absolute_magnitude": -2.51626,
  "distance": 394.014,
  "x": -0.781223,
  "y": -97.1946,
  "z": -381.837,
  "temperature": 15668.2,
  "color": 13230847
},
{
  "ra": 272.344,
  "dec": -36.6726,
  "apparent_magnitude": 5.91141,
  "absolute_magnitude": -5.09479,
  "distance": 1589.43,
  "x": 1155.72,
  "y": -279.439,
  "z": 1054.76,
  "temperature": 21324.3,
  "color": 13230847
},
{
  "ra": 34.2842,
  "dec": 56.7697,
  "apparent_magnitude": 6.00032,
  "absolute_magnitude": -3.28223,
  "distance": 718.637,
  "x": -201.823,
  "y": -628.442,
  "z": -284.196,
  "temperature": 35606.8,
  "color": 10539007
},
{
  "ra": 203.404,
  "dec": -62.3177,
  "apparent_magnitude": 6.10537,
  "absolute_magnitude": -2.73739,
  "distance": 586.884,
  "x": 498.39,
  "y": 124.08,
  "z": 283.98,
  "temperature": 15440.3,
  "color": 13230847
},
{
  "ra": 34.2399,
  "dec": 56.7188,
  "apparent_magnitude": 5.06459,
  "absolute_magnitude": -4.13648,
  "distance": 692.174,
  "x": -170.199,
  "y": -543.467,
  "z": -393.423,
  "temperature": 16562.1,
  "color": 13230847
},
{
  "ra": 332.439,
  "dec": -9.96429,
  "apparent_magnitude": 6.19943,
  "absolute_magnitude": -2.19068,
  "distance": 476.454,
  "x": 276.48,
  "y": -224.863,
  "z": 316.234,
  "temperature": 5129.02,
  "color": 16764015
},
{
  "ra": 200.568,
  "dec": -52.183,
  "apparent_magnitude": 6.6295,
  "absolute_magnitude": -5.77708,
  "distance": 3029.12,
  "x": 1154.57,
  "y": -850.512,
  "z": -2668.17,
  "temperature": 7435.07,
  "color": 16774373
},
{
  "ra": 286.743,
  "dec": -45.9705,
  "apparent_magnitude": 6.8318,
  "absolute_magnitude": -5.90267,
  "distance": 3522.85,
  "x": 2306.4,
  "y": -556.334,
  "z": -2604.13,
  "temperature": 3757.81,
  "color": 16764015
},
{
  "ra": 288.419,
  "dec": -47.5795,
  "apparent_magnitude": 4.60211,
  "absolute_magnitude": -3.09926,
  "distance": 346.956,
  "x": 279.896,
  "y": -146.201,
  "z": 143.742,
  "temperature": 5228.7,
  "color": 16776144
},
{
  "ra": 90.4511,
  "dec": 6.63882,
  "apparent_magnitude": 5.35564,
  "absolute_magnitude": -1.9757,
  "distance": 292.597,
  "x": 285.243,
  "y": -42.0755,
  "z": -49.7891,
  "temperature": 4030.8,
  "color": 16764015
},
{
  "ra": 68.9261,
  "dec": 46.8042,
  "apparent_magnitude": 6.72643,
  "absolute_magnitude": -2.89988,
  "distance": 841.904,
  "x": -65.2748,
  "y": -829.835,
  "z": -126.158,
  "temperature": 4142.49,
  "color": 16764015
},
{
  "ra": 151.887,
  "dec": -53.2601,
  "apparent_magnitude": 6.71961,
  "absolute_magnitude": -5.80685,
  "distance": 3201.06,
  "x": 868.459,
  "y": -2903.28,
  "z": -1031.27,
  "temperature": 3613.55,
  "color": 16738874
},
{
  "ra": 248.596,
  "dec": -49.7698,
  "apparent_magnitude": 6.97167,
  "absolute_magnitude": -4.39838,
  "distance": 1879.37,
  "x": 204.507,
  "y": -1859.76,
  "z": 177.415,
  "temperature": 8710.94,
  "color": 16316415
},
{
  "ra": 83.9343,
  "dec": -30.8265,
  "apparent_magnitude": 6.59137,
  "absolute_magnitude": -3.00403,
  "distance": 830.003,
  "x": 763.77,
  "y": 54.6712,
  "z": 320.269,
  "temperature": 4437.72,
  "color": 16764015
},
{
  "ra": 32.8716,
  "dec": 57.6455,
  "apparent_magnitude": 6.50841,
  "absolute_magnitude": -5.12296,
  "distance": 2119.7,
  "x": 1866.64,
  "y": -315.474,
  "z": 953.54,
  "temperature": 6710.1,
  "color": 16774373
},
{
  "ra": 297.184,
  "dec": 19.661,
  "apparent_magnitude": 6.8531,
  "absolute_magnitude": -4.04892,
  "distance": 1514.97,
  "x": 1376.95,
  "y": 62.6223,
  "z": 628.664,
  "temperature": 15303.1,
  "color": 13230847
},
{
  "ra": 194.902,
  "dec": -60.0218,
  "apparent_magnitude": 6.25171,
  "absolute_magnitude": -4.48719,
  "distance": 1405.33,
  "x": 1.22902,
  "y": -1399.2,
  "z": -131.202,
  "temperature": 3813.35,
  "color": 16764015
},
{
  "ra": 169.032,
  "dec": -53.6974,
  "apparent_magnitude": 6.52338,
  "absolute_magnitude": -1.43875,
  "distance": 391.224,
  "x": 298.106,
  "y": -146.105,
  "z": -206.984,
  "temperature": 4935.95,
  "color": 16764015
},
{
  "ra": 139.676,
  "dec": -51.5606,
  "apparent_magnitude": 6.83795,
  "absolute_magnitude": -5.6865,
  "distance": 3198.09,
  "x": 1829.53,
  "y": -677.748,
  "z": -2534.02,
  "temperature": 6596.08,
  "color": 16774373
},
{
  "ra": 174.392,
  "dec": -60.3649,
  "apparent_magnitude": 6.89589,
  "absolute_magnitude": -4.36527,
  "distance": 1787.44,
  "x": 1718.67,
  "y": 265.334,
  "z": 413.184,
  "temperature": 8594.51,
  "color": 16316415
},
{
  "ra": 225.837,
  "dec": -41.2715,
  "apparent_magnitude": 5.00082,
  "absolute_magnitude": -3.97357,
  "distance": 623.561,
  "x": 193.386,
  "y": -592.138,
  "z": 28.3321,
  "temperature": 19913,
  "color": 13230847
},
{
  "ra": 200.881,
  "dec": -59.743,
  "apparent_magnitude": 6.9689,
  "absolute_magnitude": -3.17373,
  "distance": 1067.89,
  "x": -47.5314,
  "y": -848.719,
  "z": -646.38,
  "temperature": 4435.74,
  "color": 16764015
},
{
  "ra": 150.28,
  "dec": -60.2144,
  "apparent_magnitude": 6.44397,
  "absolute_magnitude": -2.35005,
  "distance": 573.857,
  "x": 379.118,
  "y": -391.873,
  "z": 178.932,
  "temperature": 3427.34,
  "color": 16738874
},
{
  "ra": 112.486,
  "dec": -22.5659,
  "apparent_magnitude": 6.43671,
  "absolute_magnitude": -2.58336,
  "distance": 636.816,
  "x": 503.414,
  "y": -294.516,
  "z": 255.674,
  "temperature": 6092.54,
  "color": 16774373
},
{
  "ra": 62.5347,
  "dec": 53.0102,
  "apparent_magnitude": 6.51651,
  "absolute_magnitude": -2.70972,
  "distance": 700.239,
  "x": 146.054,
  "y": -684.027,
  "z": -33.3066,
  "temperature": 7522.93,
  "color": 16316415
},
{
  "ra": 105.823,
  "dec": -4.0179,
  "apparent_magnitude": 6.90526,
  "absolute_magnitude": -3.69979,
  "distance": 1321.33,
  "x": 1124.24,
  "y": -198.011,
  "z": 665.426,
  "temperature": 4351.29,
  "color": 16764015
},
{
  "ra": 21.5046,
  "dec": 81.9028,
  "apparent_magnitude": 6.92735,
  "absolute_magnitude": -1.6478,
  "distance": 518.836,
  "x": 185.745,
  "y": -344.054,
  "z": -341.051,
  "temperature": 4046.7,
  "color": 16764015
},
{
  "ra": 258.615,
  "dec": -39.7667,
  "apparent_magnitude": 6.61029,
  "absolute_magnitude": -5.9792,
  "distance": 3295.32,
  "x": 1300.62,
  "y": -1913.52,
  "z": -2346.48,
  "temperature": 4572.74,
  "color": 16764015
},
{
  "ra": 109.416,
  "dec": 38.3909,
  "apparent_magnitude": 6.81535,
  "absolute_magnitude": -2.81368,
  "distance": 842.958,
  "x": 571.83,
  "y": -463.874,
  "z": 410.377,
  "temperature": 4783.73,
  "color": 16764015
},
{
  "ra": 184.738,
  "dec": -62.4769,
  "apparent_magnitude": 5.22938,
  "absolute_magnitude": -3.0318,
  "distance": 448.989,
  "x": 383.709,
  "y": -202.348,
  "z": -115.822,
  "temperature": 4515.06,
  "color": 16764015
},
{
  "ra": 319.815,
  "dec": 58.6235,
  "apparent_magnitude": 4.26854,
  "absolute_magnitude": -6.62267,
  "distance": 1507.45,
  "x": 1061.51,
  "y": -669.193,
  "z": 835.332,
  "temperature": 6297.26,
  "color": 16774373
},
{
  "ra": 244.75,
  "dec": -53.4766,
  "apparent_magnitude": 6.95008,
  "absolute_magnitude": -2.84864,
  "distance": 911.471,
  "x": 65.5015,
  "y": -665.023,
  "z": -619.865,
  "temperature": 3520.12,
  "color": 16738874
},
{
  "ra": 301.357,
  "dec": 46.6718,
  "apparent_magnitude": 6.58007,
  "absolute_magnitude": -3.02301,
  "distance": 832.945,
  "x": 208.813,
  "y": -805.61,
  "z": 34.4464,
  "temperature": 41398.7,
  "color": 10539007
},
{
  "ra": 304.245,
  "dec": 37.6814,
  "apparent_magnitude": 5.99317,
  "absolute_magnitude": -3.70641,
  "distance": 870.795,
  "x": 196.671,
  "y": -344.516,
  "z": -775.186,
  "temperature": 21039.2,
  "color": 13230847
},
{
  "ra": 294.781,
  "dec": 40.6268,
  "apparent_magnitude": 5.15627,
  "absolute_magnitude": -3.53444,
  "distance": 547.196,
  "x": 267.69,
  "y": -305.462,
  "z": -366.686,
  "temperature": 26700.9,
  "color": 13230847
},
{
  "ra": 269.505,
  "dec": -22.1728,
  "apparent_magnitude": 6.60736,
  "absolute_magnitude": -2.28071,
  "distance": 599.259,
  "x": 409.832,
  "y": -101.445,
  "z": -425.273,
  "temperature": 16875.8,
  "color": 13230847
},
{
  "ra": 99.9428,
  "dec": -34.8713,
  "apparent_magnitude": 6.6753,
  "absolute_magnitude": -1.79758,
  "distance": 494.969,
  "x": 375.38,
  "y": -252.339,
  "z": -201.02,
  "temperature": 4606.3,
  "color": 16764015
},
{
  "ra": 274.667,
  "dec": -42.2884,
  "apparent_magnitude": 6.8592,
  "absolute_magnitude": -4.92408,
  "distance": 2273.3,
  "x": 1813.22,
  "y": -974.029,
  "z": 965.076,
  "temperature": 19974.5,
  "color": 13230847
},
{
  "ra": 253.499,
  "dec": -42.362,
  "apparent_magnitude": 5.26888,
  "absolute_magnitude": -6.63594,
  "distance": 2404.17,
  "x": 1814.4,
  "y": -1249.89,
  "z": 962.182,
  "temperature": 6105.94,
  "color": 16774373
},
{
  "ra": 118.847,
  "dec": -22.0226,
  "apparent_magnitude": 6.38935,
  "absolute_magnitude": -3.16504,
  "distance": 814.477,
  "x": 298.539,
  "y": -313.103,
  "z": -690.082,
  "temperature": 4519.33,
  "color": 16764015
},
{
  "ra": 99.6591,
  "dec": 1.61351,
  "apparent_magnitude": 6.80548,
  "absolute_magnitude": -4.96859,
  "distance": 2263.67,
  "x": 1720.13,
  "y": -1124.85,
  "z": 948.715,
  "temperature": 23313.4,
  "color": 13230847
},
{
  "ra": 73.5125,
  "dec": 66.3427,
  "apparent_magnitude": 5.18858,
  "absolute_magnitude": -6.9271,
  "distance": 2649.33,
  "x": 2254.91,
  "y": 318.731,
  "z": -1353.79,
  "temperature": 9997.99,
  "color": 16316415
},
{
  "ra": 260.499,
  "dec": -37.5211,
  "apparent_magnitude": 6.56612,
  "absolute_magnitude": -3.19818,
  "distance": 897.139,
  "x": 156.621,
  "y": -763.455,
  "z": -444.37,
  "temperature": 5276.86,
  "color": 16776144
},
{
  "ra": 161.461,
  "dec": -59.4887,
  "apparent_magnitude": 6.86502,
  "absolute_magnitude": -5.17672,
  "distance": 2560.64,
  "x": 2295.61,
  "y": 358.895,
  "z": -1076.23,
  "temperature": 3566.15,
  "color": 16738874
},
{
  "ra": 128.097,
  "dec": -49.6013,
  "apparent_magnitude": 5.47522,
  "absolute_magnitude": -4.28477,
  "distance": 895.363,
  "x": 783.808,
  "y": -338.992,
  "z": 269.079,
  "temperature": 17315.4,
  "color": 13230847
},
{
  "ra": 297.881,
  "dec": 19.1784,
  "apparent_magnitude": 6.66484,
  "absolute_magnitude": -2.27195,
  "distance": 612.854,
  "x": 461.11,
  "y": -342.09,
  "z": -214.34,
  "temperature": 3639.09,
  "color": 16738874
},
{
  "ra": 102.53,
  "dec": -5.81133,
  "apparent_magnitude": 6.67686,
  "absolute_magnitude": -3.67099,
  "distance": 1173.74,
  "x": 1165.95,
  "y": 134.851,
  "z": -5.88046,
  "temperature": 4732.53,
  "color": 16764015
},
{
  "ra": 272.678,
  "dec": 25.5203,
  "apparent_magnitude": 6.84701,
  "absolute_magnitude": -2.29238,
  "distance": 672.79,
  "x": 585.411,
  "y": -299.533,
  "z": -142.196,
  "temperature": 5320.06,
  "color": 16776144
},
{
  "ra": 339.027,
  "dec": -16.3881,
  "apparent_magnitude": 5.98603,
  "absolute_magnitude": -4.17183,
  "distance": 1075.4,
  "x": 597.018,
  "y": -862.587,
  "z": 236.657,
  "temperature": 23439.4,
  "color": 13230847
},
{
  "ra": 125.026,
  "dec": 2.7656,
  "apparent_magnitude": 6.11821,
  "absolute_magnitude": -3.19521,
  "distance": 728.927,
  "x": 622.482,
  "y": -332.964,
  "z": -181.619,
  "temperature": 4574.05,
  "color": 16764015
},
{
  "ra": 127.624,
  "dec": -36.7213,
  "apparent_magnitude": 5.66416,
  "absolute_magnitude": -5.33355,
  "distance": 1583.23,
  "x": 1442.3,
  "y": -390.248,
  "z": 523.532,
  "temperature": 3695.43,
  "color": 16738874
},
{
  "ra": 298.007,
  "dec": 24.9921,
  "apparent_magnitude": 4.73003,
  "absolute_magnitude": -5.60619,
  "distance": 1167.47,
  "x": 405.407,
  "y": -531.605,
  "z": -957.089,
  "temperature": 7592.41,
  "color": 16316415
},
{
  "ra": 129.411,
  "dec": -42.989,
  "apparent_magnitude": 6.54424,
  "absolute_magnitude": -4.99273,
  "distance": 2029.53,
  "x": 1471.14,
  "y": -1384.86,
  "z": -192.049,
  "temperature": 7898.94,
  "color": 16316415
},
{
  "ra": 216.276,
  "dec": -68.1954,
  "apparent_magnitude": 6.5859,
  "absolute_magnitude": -4.39908,
  "distance": 1573.97,
  "x": 1278.67,
  "y": -917.658,
  "z": -16.3868,
  "temperature": 7294.13,
  "color": 16774373
},
{
  "ra": 83.182,
  "dec": 32.192,
  "apparent_magnitude": 5.73415,
  "absolute_magnitude": -5.61889,
  "distance": 1864.7,
  "x": 1821.79,
  "y": -396.829,
  "z": 27.1684,
  "temperature": 15015.9,
  "color": 13230847
},
{
  "ra": 330.519,
  "dec": 58.0004,
  "apparent_magnitude": 6.89634,
  "absolute_magnitude": -4.73041,
  "distance": 2115.19,
  "x": 1662.53,
  "y": -1259.7,
  "z": 350.995,
  "temperature": 24865.8,
  "color": 13230847
},
{
  "ra": 81.1192,
  "dec": -2.39715,
  "apparent_magnitude": 6.14559,
  "absolute_magnitude": -5.39368,
  "distance": 2031.67,
  "x": 1372.41,
  "y": -931.848,
  "z": -1172.97,
  "temperature": 18608.2,
  "color": 13230847
},
{
  "ra": 129.411,
  "dec": -42.989,
  "apparent_magnitude": 6.54424,
  "absolute_magnitude": -4.99273,
  "distance": 2029.53,
  "x": 1471.14,
  "y": -1384.86,
  "z": -192.049,
  "temperature": 7898.94,
  "color": 16316415
},
{
  "ra": 130.567,
  "dec": -48.0991,
  "apparent_magnitude": 6.59608,
  "absolute_magnitude": -4.63648,
  "distance": 1764.06,
  "x": 1654.11,
  "y": -599.16,
  "z": 129.668,
  "temperature": 19819.9,
  "color": 13230847
},
{
  "ra": 130.305,
  "dec": -47.3171,
  "apparent_magnitude": 6.92296,
  "absolute_magnitude": -4.55601,
  "distance": 1976.04,
  "x": 1816.34,
  "y": -486.325,
  "z": -607.573,
  "temperature": 7890.94,
  "color": 16316415
},
{
  "ra": 269.739,
  "dec": -22.5176,
  "apparent_magnitude": 6.3608,
  "absolute_magnitude": -3.69028,
  "distance": 1023.8,
  "x": 742.187,
  "y": -699.932,
  "z": -86.1661,
  "temperature": 6677.9,
  "color": 16774373
},
{
  "ra": 269.86,
  "dec": -22.4669,
  "apparent_magnitude": 6.86222,
  "absolute_magnitude": -3.22821,
  "distance": 1042.52,
  "x": 641.664,
  "y": -810.729,
  "z": -133.557,
  "temperature": 19890.4,
  "color": 13230847
},
{
  "ra": 241.315,
  "dec": -56.3399,
  "apparent_magnitude": 6.17318,
  "absolute_magnitude": -4.20393,
  "distance": 1189.66,
  "x": 889.083,
  "y": -595.128,
  "z": -520.237,
  "temperature": 3784.44,
  "color": 16764015
},
{
  "ra": 339.115,
  "dec": 58.4261,
  "apparent_magnitude": 6.17151,
  "absolute_magnitude": -11.5547,
  "distance": 35095.4,
  "x": -9031.67,
  "y": 753.379,
  "z": 33905,
  "temperature": 4871.35,
  "color": 16764015
},
{
  "ra": 273.804,
  "dec": -20.388,
  "apparent_magnitude": 6.01316,
  "absolute_magnitude": -10.0662,
  "distance": 16439.1,
  "x": 1320.4,
  "y": -1415.69,
  "z": -16324.7,
  "temperature": 21691.1,
  "color": 13230847
},
{
  "ra": 102.719,
  "dec": -0.0731912,
  "apparent_magnitude": 6.70107,
  "absolute_magnitude": -6.82735,
  "distance": 5077.9,
  "x": -2196.01,
  "y": 4405.74,
  "z": -1245.84,
  "temperature": 3679.72,
  "color": 16738874
},
{
  "ra": 338.8,
  "dec": 14.6105,
  "apparent_magnitude": 6.68002,
  "absolute_magnitude": -6.61946,
  "distance": 4569.8,
  "x": -613.436,
  "y": 94.1429,
  "z": 4527.46,
  "temperature": 5208.01,
  "color": 16776144
},
{
  "ra": 337.545,
  "dec": 57.0008,
  "apparent_magnitude": 6.95103,
  "absolute_magnitude": -6.76153,
  "distance": 5527.28,
  "x": 1036.03,
  "y": -5276.86,
  "z": 1277.61,
  "temperature": 3722.13,
  "color": 16764015
},
{
  "ra": 333.289,
  "dec": 53.6239,
  "apparent_magnitude": 6.93637,
  "absolute_magnitude": -5.77864,
  "distance": 3491.43,
  "x": -2076.92,
  "y": -2288.23,
  "z": -1624.95,
  "temperature": 3685.42,
  "color": 16738874
},
{
  "ra": 116.291,
  "dec": -24.6527,
  "apparent_magnitude": 6.65425,
  "absolute_magnitude": -5.17908,
  "distance": 2326.31,
  "x": -1598.06,
  "y": -1355.09,
  "z": 1010.75,
  "temperature": 8915.46,
  "color": 16316415
},
{
  "ra": 115.261,
  "dec": -31.6831,
  "apparent_magnitude": 6.60549,
  "absolute_magnitude": -5.3806,
  "distance": 2495.85,
  "x": -234.014,
  "y": 1789.76,
  "z": -1723.73,
  "temperature": 3734.59,
  "color": 16764015
},
{
  "ra": 332.16,
  "dec": 59.5504,
  "apparent_magnitude": 5.96005,
  "absolute_magnitude": -5.20692,
  "distance": 1711.57,
  "x": -652.888,
  "y": 1565.58,
  "z": -228.432,
  "temperature": 4546.51,
  "color": 16764015
},
{
  "ra": 107.794,
  "dec": -4.7033,
  "apparent_magnitude": 6.88406,
  "absolute_magnitude": -5.89621,
  "distance": 3597.94,
  "x": 1748.21,
  "y": -1207.75,
  "z": 2903.49,
  "temperature": 8442.75,
  "color": 16316415
},
{
  "ra": 156.566,
  "dec": -54.5215,
  "apparent_magnitude": 6.33009,
  "absolute_magnitude": -5.64665,
  "distance": 2485.13,
  "x": 416.351,
  "y": -419.087,
  "z": 2413.89,
  "temperature": 3712.74,
  "color": 16764015
},
{
  "ra": 118.917,
  "dec": -28.6485,
  "apparent_magnitude": 4.76736,
  "absolute_magnitude": -5.63865,
  "distance": 1205.59,
  "x": -1070.52,
  "y": 236.392,
  "z": 501.556,
  "temperature": 3637.48,
  "color": 16738874
},
{
  "ra": 202.229,
  "dec": -62.1023,
  "apparent_magnitude": 6.14789,
  "absolute_magnitude": -6.41416,
  "distance": 3253.94,
  "x": 2723.34,
  "y": 1057.87,
  "z": 1432.64,
  "temperature": 8199.93,
  "color": 16316415
},
{
  "ra": 162.307,
  "dec": -60.1842,
  "apparent_magnitude": 6.62099,
  "absolute_magnitude": -4.29249,
  "distance": 1522.99,
  "x": 387.101,
  "y": 1258.6,
  "z": 765.237,
  "temperature": 15107.2,
  "color": 13230847
},
{
  "ra": 264.042,
  "dec": -33.4946,
  "apparent_magnitude": 6.86548,
  "absolute_magnitude": -6.02253,
  "distance": 3780.96,
  "x": 249.057,
  "y": -1407.08,
  "z": -3500.53,
  "temperature": 4618.49,
  "color": 16764015
},
{
  "ra": 15.1373,
  "dec": 63.0288,
  "apparent_magnitude": 5.07406,
  "absolute_magnitude": -4.47491,
  "distance": 812.445,
  "x": -690.336,
  "y": 396.918,
  "z": -161.12,
  "temperature": 7869.96,
  "color": 16316415
},
{
  "ra": 109.758,
  "dec": -19.2803,
  "apparent_magnitude": 5.31349,
  "absolute_magnitude": -6.41722,
  "distance": 2218.93,
  "x": -816.11,
  "y": -662.714,
  "z": -1954.07,
  "temperature": 7867.96,
  "color": 16316415
},
{
  "ra": 112.966,
  "dec": -22.7011,
  "apparent_magnitude": 6.91936,
  "absolute_magnitude": -3.89008,
  "distance": 1451.74,
  "x": -342.284,
  "y": -902.385,
  "z": 1084.48,
  "temperature": 4807.06,
  "color": 16764015
},
{
  "ra": 345.522,
  "dec": 59.8184,
  "apparent_magnitude": 6.70809,
  "absolute_magnitude": -4.50133,
  "distance": 1745.36,
  "x": -888.256,
  "y": -1038.03,
  "z": -1086.17,
  "temperature": 4291.66,
  "color": 16764015
},
{
  "ra": 187.38,
  "dec": -66.8605,
  "apparent_magnitude": 6.24581,
  "absolute_magnitude": -4.91342,
  "distance": 1705.48,
  "x": 1027.93,
  "y": 330.598,
  "z": 1320.12,
  "temperature": 6651,
  "color": 16774373
},
{
  "ra": 5.35116,
  "dec": 59.9531,
  "apparent_magnitude": 6.95311,
  "absolute_magnitude": -4.18557,
  "distance": 1689.41,
  "x": 247.149,
  "y": 865.91,
  "z": -1429.42,
  "temperature": 3834.41,
  "color": 16764015
},
{
  "ra": 168.81,
  "dec": -60.1646,
  "apparent_magnitude": 5.02411,
  "absolute_magnitude": -4.34712,
  "distance": 748.593,
  "x": 195.262,
  "y": 557.789,
  "z": 459.495,
  "temperature": 22712.3,
  "color": 13230847
},
{
  "ra": 184.974,
  "dec": -62.8542,
  "apparent_magnitude": 4.76692,
  "absolute_magnitude": -5.33261,
  "distance": 1046.9,
  "x": -636.726,
  "y": -219.582,
  "z": -801.474,
  "temperature": 7678.69,
  "color": 16316415
},
{
  "ra": 36.6958,
  "dec": 58.8759,
  "apparent_magnitude": 6.59233,
  "absolute_magnitude": -4.17337,
  "distance": 1422.78,
  "x": 820.462,
  "y": 304.214,
  "z": 1121.88,
  "temperature": 17327.8,
  "color": 13230847
},
{
  "ra": 313.958,
  "dec": 47.4176,
  "apparent_magnitude": 4.71372,
  "absolute_magnitude": -6.50466,
  "distance": 1752.57,
  "x": -628.518,
  "y": -690.302,
  "z": -1483.22,
  "temperature": 15024.6,
  "color": 13230847
},
{
  "ra": 14.6118,
  "dec": 63.7136,
  "apparent_magnitude": 6.55576,
  "absolute_magnitude": -4.49286,
  "distance": 1620.78,
  "x": 1024.56,
  "y": 264.179,
  "z": 1227.77,
  "temperature": 16059,
  "color": 13230847
},
{
  "ra": 172.274,
  "dec": -56.6442,
  "apparent_magnitude": 6.41006,
  "absolute_magnitude": -3.7686,
  "distance": 1085.75,
  "x": -446.582,
  "y": 68.4517,
  "z": -987.288,
  "temperature": 30746.2,
  "color": 10539007
},
{
  "ra": 33.7771,
  "dec": 56.9265,
  "apparent_magnitude": 5.11222,
  "absolute_magnitude": -3.49885,
  "distance": 527.491,
  "x": 87.387,
  "y": 482.534,
  "z": 194.349,
  "temperature": 17996.4,
  "color": 13230847
},
{
  "ra": 172.313,
  "dec": -63.5539,
  "apparent_magnitude": 6.26742,
  "absolute_magnitude": -5.667,
  "distance": 2437.16,
  "x": 78.0311,
  "y": -312.668,
  "z": -2415.76,
  "temperature": 6941.35,
  "color": 16774373
},
{
  "ra": 34.722,
  "dec": 57.4213,
  "apparent_magnitude": 6.76407,
  "absolute_magnitude": -4.60367,
  "distance": 1877.36,
  "x": 169.323,
  "y": -1445.43,
  "z": 1185.98,
  "temperature": 3638.37,
  "color": 16738874
},
{
  "ra": 247.597,
  "dec": -37.9726,
  "apparent_magnitude": 6.41838,
  "absolute_magnitude": -4.38024,
  "distance": 1444.52,
  "x": -231.435,
  "y": 153.817,
  "z": -1417.54,
  "temperature": 17792.5,
  "color": 13230847
},
{
  "ra": 105.164,
  "dec": -9.20296,
  "apparent_magnitude": 6.54379,
  "absolute_magnitude": -5.56942,
  "distance": 2646.32,
  "x": 1958.4,
  "y": 1227.82,
  "z": -1288.46,
  "temperature": 6968.23,
  "color": 16774373
},
{
  "ra": 197.39,
  "dec": -62.871,
  "apparent_magnitude": 6.24793,
  "absolute_magnitude": -3.55764,
  "distance": 914.353,
  "x": -355.455,
  "y": 63.5002,
  "z": -840.037,
  "temperature": 6335.87,
  "color": 16774373
},
{
  "ra": 29.962,
  "dec": 59.1608,
  "apparent_magnitude": 6.36758,
  "absolute_magnitude": -4.93709,
  "distance": 1823.62,
  "x": 1524.42,
  "y": 882.716,
  "z": 471.734,
  "temperature": 4535.5,
  "color": 16764015
},
{
  "ra": 39.6059,
  "dec": 57.0462,
  "apparent_magnitude": 5.32147,
  "absolute_magnitude": -5.40984,
  "distance": 1400.43,
  "x": 1072.67,
  "y": 806.901,
  "z": 399.362,
  "temperature": 3730.5,
  "color": 16764015
},
{
  "ra": 154.291,
  "dec": -55.9225,
  "apparent_magnitude": 6.64629,
  "absolute_magnitude": -4.81602,
  "distance": 1960.93,
  "x": -46.7866,
  "y": -1848.06,
  "z": 654.002,
  "temperature": 3704.85,
  "color": 16764015
},
{
  "ra": 153.019,
  "dec": -49.7483,
  "apparent_magnitude": 6.50832,
  "absolute_magnitude": -3.04449,
  "distance": 813.885,
  "x": 516.381,
  "y": 459.821,
  "z": 429.33,
  "temperature": 4199.62,
  "color": 16764015
},
{
  "ra": 162.365,
  "dec": -60.2947,
  "apparent_magnitude": 6.17716,
  "absolute_magnitude": -3.90623,
  "distance": 1039.15,
  "x": 708.981,
  "y": 460.326,
  "z": 604.381,
  "temperature": 6052.01,
  "color": 16774373
},
{
  "ra": 35.1208,
  "dec": 56.9931,
  "apparent_magnitude": 6.6333,
  "absolute_magnitude": -5.19633,
  "distance": 2322.34,
  "x": -18.1121,
  "y": -2307.49,
  "z": 261.628,
  "temperature": 3681.45,
  "color": 16738874
},
{
  "ra": 34.7685,
  "dec": 57.1355,
  "apparent_magnitude": 5.75351,
  "absolute_magnitude": -5.36155,
  "distance": 1671.14,
  "x": -105.96,
  "y": -1581.38,
  "z": 529.824,
  "temperature": 16526.1,
  "color": 13230847
},
{
  "ra": 162.23,
  "dec": -59.4468,
  "apparent_magnitude": 6.99767,
  "absolute_magnitude": -4.21413,
  "distance": 1747.27,
  "x": 823.508,
  "y": 833.61,
  "z": -1296.1,
  "temperature": 17074.6,
  "color": 13230847
},
{
  "ra": 134.37,
  "dec": -50.7495,
  "apparent_magnitude": 6.55222,
  "absolute_magnitude": -4.74393,
  "distance": 1816.48,
  "x": 265.031,
  "y": 132.25,
  "z": -1792.16,
  "temperature": 22928.9,
  "color": 13230847
},
{
  "ra": 326.57,
  "dec": 53.0095,
  "apparent_magnitude": 6.94688,
  "absolute_magnitude": -2.85111,
  "distance": 911.164,
  "x": -275.496,
  "y": -859.574,
  "z": 124.32,
  "temperature": 4843.57,
  "color": 16764015
},
{
  "ra": 112.532,
  "dec": -9.38813,
  "apparent_magnitude": 6.21054,
  "absolute_magnitude": -3.39804,
  "distance": 835.059,
  "x": -123.127,
  "y": 18.7052,
  "z": -825.719,
  "temperature": 3403.29,
  "color": 16738874
},
{
  "ra": 193.422,
  "dec": -60.3494,
  "apparent_magnitude": 5.42141,
  "absolute_magnitude": -5.60636,
  "distance": 1605.29,
  "x": 1398.3,
  "y": 512.921,
  "z": 598.853,
  "temperature": 3670.54,
  "color": 16738874
},
{
  "ra": 163.042,
  "dec": -59.9552,
  "apparent_magnitude": 6.18127,
  "absolute_magnitude": -2.67729,
  "distance": 591.168,
  "x": -204.859,
  "y": -524.493,
  "z": -180.057,
  "temperature": 21237.6,
  "color": 13230847
},
{
  "ra": 304.345,
  "dec": 38.2357,
  "apparent_magnitude": 4.08459,
  "absolute_magnitude": -4.80085,
  "distance": 598.532,
  "x": 56.4056,
  "y": -477.898,
  "z": 355.911,
  "temperature": 18202.6,
  "color": 13230847
},
{
  "ra": 265.985,
  "dec": -6.26912,
  "apparent_magnitude": 6.84045,
  "absolute_magnitude": -3.57037,
  "distance": 1208.27,
  "x": 700.53,
  "y": 678.262,
  "z": -713.54,
  "temperature": 7749.31,
  "color": 16316415
},
{
  "ra": 166.192,
  "dec": -43.6828,
  "apparent_magnitude": 6.49194,
  "absolute_magnitude": -2.36701,
  "distance": 591.276,
  "x": -164.842,
  "y": -555.69,
  "z": -116.803,
  "temperature": 4984.07,
  "color": 16764015
},
{
  "ra": 160.669,
  "dec": -59.2157,
  "apparent_magnitude": 6.58551,
  "absolute_magnitude": -6.361,
  "distance": 3884.2,
  "x": 3467.22,
  "y": -363.501,
  "z": -1712.69,
  "temperature": 15104.5,
  "color": 13230847
},
{
  "ra": 285.115,
  "dec": 56.5253,
  "apparent_magnitude": 6.846,
  "absolute_magnitude": -2.87911,
  "distance": 881.094,
  "x": 252.62,
  "y": 289.033,
  "z": -793.076,
  "temperature": 19279.5,
  "color": 13230847
},
{
  "ra": 269.54,
  "dec": -28.1417,
  "apparent_magnitude": 6.84677,
  "absolute_magnitude": -3.21324,
  "distance": 1028.02,
  "x": 86.4321,
  "y": 62.9982,
  "z": -1022.44,
  "temperature": 23714.3,
  "color": 13230847
},
{
  "ra": 68.5653,
  "dec": 34.3847,
  "apparent_magnitude": 5.4613,
  "absolute_magnitude": -2.51626,
  "distance": 394.014,
  "x": -0.781223,
  "y": -97.1946,
  "z": -381.837,
  "temperature": 15668.2,
  "color": 13230847
},
{
  "ra": 272.344,
  "dec": -36.6726,
  "apparent_magnitude": 5.91141,
  "absolute_magnitude": -5.09479,
  "distance": 1589.43,
  "x": 1155.72,
  "y": -279.439,
  "z": 1054.76,
  "temperature": 21324.3,
  "color": 13230847
},
{
  "ra": 34.2842,
  "dec": 56.7697,
  "apparent_magnitude": 6.00032,
  "absolute_magnitude": -3.28223,
  "distance": 718.637,
  "x": -201.823,
  "y": -628.442,
  "z": -284.196,
  "temperature": 35606.8,
  "color": 10539007
},
{
  "ra": 203.404,
  "dec": -62.3177,
  "apparent_magnitude": 6.10537,
  "absolute_magnitude": -2.73739,
  "distance": 586.884,
  "x": 498.39,
  "y": 124.08,
  "z": 283.98,
  "temperature": 15440.3,
  "color": 13230847
},
{
  "ra": 34.2399,
  "dec": 56.7188,
  "apparent_magnitude": 5.06459,
  "absolute_magnitude": -4.13648,
  "distance": 692.174,
  "x": -170.199,
  "y": -543.467,
  "z": -393.423,
  "temperature": 16562.1,
  "color": 13230847
},
{
  "ra": 332.439,
  "dec": -9.96429,
  "apparent_magnitude": 6.19943,
  "absolute_magnitude": -2.19068,
  "distance": 476.454,
  "x": 276.48,
  "y": -224.863,
  "z": 316.234,
  "temperature": 5129.02,
  "color": 16764015
},
{
  "ra": 200.568,
  "dec": -52.183,
  "apparent_magnitude": 6.6295,
  "absolute_magnitude": -5.77708,
  "distance": 3029.12,
  "x": 1154.57,
  "y": -850.512,
  "z": -2668.17,
  "temperature": 7435.07,
  "color": 16774373
},
{
  "ra": 286.743,
  "dec": -45.9705,
  "apparent_magnitude": 6.8318,
  "absolute_magnitude": -5.90267,
  "distance": 3522.85,
  "x": 2306.4,
  "y": -556.334,
  "z": -2604.13,
  "temperature": 3757.81,
  "color": 16764015
},
{
  "ra": 288.419,
  "dec": -47.5795,
  "apparent_magnitude": 4.60211,
  "absolute_magnitude": -3.09926,
  "distance": 346.956,
  "x": 279.896,
  "y": -146.201,
  "z": 143.742,
  "temperature": 5228.7,
  "color": 16776144
},
{
  "ra": 90.4511,
  "dec": 6.63882,
  "apparent_magnitude": 5.35564,
  "absolute_magnitude": -1.9757,
  "distance": 292.597,
  "x": 285.243,
  "y": -42.0755,
  "z": -49.7891,
  "temperature": 4030.8,
  "color": 16764015
},
{
  "ra": 68.9261,
  "dec": 46.8042,
  "apparent_magnitude": 6.72643,
  "absolute_magnitude": -2.89988,
  "distance": 841.904,
  "x": -65.2748,
  "y": -829.835,
  "z": -126.158,
  "temperature": 4142.49,
  "color": 16764015
},
{
  "ra": 151.887,
  "dec": -53.2601,
  "apparent_magnitude": 6.71961,
  "absolute_magnitude": -5.80685,
  "distance": 3201.06,
  "x": 868.459,
  "y": -2903.28,
  "z": -1031.27,
  "temperature": 3613.55,
  "color": 16738874
},
{
  "ra": 248.596,
  "dec": -49.7698,
  "apparent_magnitude": 6.97167,
  "absolute_magnitude": -4.39838,
  "distance": 1879.37,
  "x": 204.507,
  "y": -1859.76,
  "z": 177.415,
  "temperature": 8710.94,
  "color": 16316415
},
{
  "ra": 83.9343,
  "dec": -30.8265,
  "apparent_magnitude": 6.59137,
  "absolute_magnitude": -3.00403,
  "distance": 830.003,
  "x": 763.77,
  "y": 54.6712,
  "z": 320.269,
  "temperature": 4437.72,
  "color": 16764015
},
{
  "ra": 32.8716,
  "dec": 57.6455,
  "apparent_magnitude": 6.50841,
  "absolute_magnitude": -5.12296,
  "distance": 2119.7,
  "x": 1866.64,
  "y": -315.474,
  "z": 953.54,
  "temperature": 6710.1,
  "color": 16774373
},
{
  "ra": 297.184,
  "dec": 19.661,
  "apparent_magnitude": 6.8531,
  "absolute_magnitude": -4.04892,
  "distance": 1514.97,
  "x": 1376.95,
  "y": 62.6223,
  "z": 628.664,
  "temperature": 15303.1,
  "color": 13230847
},
{
  "ra": 194.902,
  "dec": -60.0218,
  "apparent_magnitude": 6.25171,
  "absolute_magnitude": -4.48719,
  "distance": 1405.33,
  "x": 1.22902,
  "y": -1399.2,
  "z": -131.202,
  "temperature": 3813.35,
  "color": 16764015
},
{
  "ra": 169.032,
  "dec": -53.6974,
  "apparent_magnitude": 6.52338,
  "absolute_magnitude": -1.43875,
  "distance": 391.224,
  "x": 298.106,
  "y": -146.105,
  "z": -206.984,
  "temperature": 4935.95,
  "color": 16764015
},
{
  "ra": 139.676,
  "dec": -51.5606,
  "apparent_magnitude": 6.83795,
  "absolute_magnitude": -5.6865,
  "distance": 3198.09,
  "x": 1829.53,
  "y": -677.748,
  "z": -2534.02,
  "temperature": 6596.08,
  "color": 16774373
},
{
  "ra": 174.392,
  "dec": -60.3649,
  "apparent_magnitude": 6.89589,
  "absolute_magnitude": -4.36527,
  "distance": 1787.44,
  "x": 1718.67,
  "y": 265.334,
  "z": 413.184,
  "temperature": 8594.51,
  "color": 16316415
},
{
  "ra": 225.837,
  "dec": -41.2715,
  "apparent_magnitude": 5.00082,
  "absolute_magnitude": -3.97357,
  "distance": 623.561,
  "x": 193.386,
  "y": -592.138,
  "z": 28.3321,
  "temperature": 19913,
  "color": 13230847
},
{
  "ra": 200.881,
  "dec": -59.743,
  "apparent_magnitude": 6.9689,
  "absolute_magnitude": -3.17373,
  "distance": 1067.89,
  "x": -47.5314,
  "y": -848.719,
  "z": -646.38,
  "temperature": 4435.74,
  "color": 16764015
},
{
  "ra": 150.28,
  "dec": -60.2144,
  "apparent_magnitude": 6.44397,
  "absolute_magnitude": -2.35005,
  "distance": 573.857,
  "x": 379.118,
  "y": -391.873,
  "z": 178.932,
  "temperature": 3427.34,
  "color": 16738874
},
{
  "ra": 112.486,
  "dec": -22.5659,
  "apparent_magnitude": 6.43671,
  "absolute_magnitude": -2.58336,
  "distance": 636.816,
  "x": 503.414,
  "y": -294.516,
  "z": 255.674,
  "temperature": 6092.54,
  "color": 16774373
},
{
  "ra": 62.5347,
  "dec": 53.0102,
  "apparent_magnitude": 6.51651,
  "absolute_magnitude": -2.70972,
  "distance": 700.239,
  "x": 146.054,
  "y": -684.027,
  "z": -33.3066,
  "temperature": 7522.93,
  "color": 16316415
},
{
  "ra": 105.823,
  "dec": -4.0179,
  "apparent_magnitude": 6.90526,
  "absolute_magnitude": -3.69979,
  "distance": 1321.33,
  "x": 1124.24,
  "y": -198.011,
  "z": 665.426,
  "temperature": 4351.29,
  "color": 16764015
},
{
  "ra": 21.5046,
  "dec": 81.9028,
  "apparent_magnitude": 6.92735,
  "absolute_magnitude": -1.6478,
  "distance": 518.836,
  "x": 185.745,
  "y": -344.054,
  "z": -341.051,
  "temperature": 4046.7,
  "color": 16764015
},
{
  "ra": 258.615,
  "dec": -39.7667,
  "apparent_magnitude": 6.61029,
  "absolute_magnitude": -5.9792,
  "distance": 3295.32,
  "x": 1300.62,
  "y": -1913.52,
  "z": -2346.48,
  "temperature": 4572.74,
  "color": 16764015
},
{
  "ra": 109.416,
  "dec": 38.3909,
  "apparent_magnitude": 6.81535,
  "absolute_magnitude": -2.81368,
  "distance": 842.958,
  "x": 571.83,
  "y": -463.874,
  "z": 410.377,
  "temperature": 4783.73,
  "color": 16764015
},
{
  "ra": 184.738,
  "dec": -62.4769,
  "apparent_magnitude": 5.22938,
  "absolute_magnitude": -3.0318,
  "distance": 448.989,
  "x": 383.709,
  "y": -202.348,
  "z": -115.822,
  "temperature": 4515.06,
  "color": 16764015
},
{
  "ra": 319.815,
  "dec": 58.6235,
  "apparent_magnitude": 4.26854,
  "absolute_magnitude": -6.62267,
  "distance": 1507.45,
  "x": 1061.51,
  "y": -669.193,
  "z": 835.332,
  "temperature": 6297.26,
  "color": 16774373
},
{
  "ra": 244.75,
  "dec": -53.4766,
  "apparent_magnitude": 6.95008,
  "absolute_magnitude": -2.84864,
  "distance": 911.471,
  "x": 65.5015,
  "y": -665.023,
  "z": -619.865,
  "temperature": 3520.12,
  "color": 16738874
},
{
  "ra": 301.357,
  "dec": 46.6718,
  "apparent_magnitude": 6.58007,
  "absolute_magnitude": -3.02301,
  "distance": 832.945,
  "x": 208.813,
  "y": -805.61,
  "z": 34.4464,
  "temperature": 41398.7,
  "color": 10539007
},
{
  "ra": 304.245,
  "dec": 37.6814,
  "apparent_magnitude": 5.99317,
  "absolute_magnitude": -3.70641,
  "distance": 870.795,
  "x": 196.671,
  "y": -344.516,
  "z": -775.186,
  "temperature": 21039.2,
  "color": 13230847
},
{
  "ra": 294.781,
  "dec": 40.6268,
  "apparent_magnitude": 5.15627,
  "absolute_magnitude": -3.53444,
  "distance": 547.196,
  "x": 267.69,
  "y": -305.462,
  "z": -366.686,
  "temperature": 26700.9,
  "color": 13230847
},
{
  "ra": 269.505,
  "dec": -22.1728,
  "apparent_magnitude": 6.60736,
  "absolute_magnitude": -2.28071,
  "distance": 599.259,
  "x": 409.832,
  "y": -101.445,
  "z": -425.273,
  "temperature": 16875.8,
  "color": 13230847
},
{
  "ra": 99.9428,
  "dec": -34.8713,
  "apparent_magnitude": 6.6753,
  "absolute_magnitude": -1.79758,
  "distance": 494.969,
  "x": 375.38,
  "y": -252.339,
  "z": -201.02,
  "temperature": 4606.3,
  "color": 16764015
},
{
  "ra": 274.667,
  "dec": -42.2884,
  "apparent_magnitude": 6.8592,
  "absolute_magnitude": -4.92408,
  "distance": 2273.3,
  "x": 1813.22,
  "y": -974.029,
  "z": 965.076,
  "temperature": 19974.5,
  "color": 13230847
},
{
  "ra": 253.499,
  "dec": -42.362,
  "apparent_magnitude": 5.26888,
  "absolute_magnitude": -6.63594,
  "distance": 2404.17,
  "x": 1814.4,
  "y": -1249.89,
  "z": 962.182,
  "temperature": 6105.94,
  "color": 16774373
},
{
  "ra": 118.847,
  "dec": -22.0226,
  "apparent_magnitude": 6.38935,
  "absolute_magnitude": -3.16504,
  "distance": 814.477,
  "x": 298.539,
  "y": -313.103,
  "z": -690.082,
  "temperature": 4519.33,
  "color": 16764015
},
{
  "ra": 99.6591,
  "dec": 1.61351,
  "apparent_magnitude": 6.80548,
  "absolute_magnitude": -4.96859,
  "distance": 2263.67,
  "x": 1720.13,
  "y": -1124.85,
  "z": 948.715,
  "temperature": 23313.4,
  "color": 13230847
},
{
  "ra": 73.5125,
  "dec": 66.3427,
  "apparent_magnitude": 5.18858,
  "absolute_magnitude": -6.9271,
  "distance": 2649.33,
  "x": 2254.91,
  "y": 318.731,
  "z": -1353.79,
  "temperature": 9997.99,
  "color": 16316415
},
{
  "ra": 260.499,
  "dec": -37.5211,
  "apparent_magnitude": 6.56612,
  "absolute_magnitude": -3.19818,
  "distance": 897.139,
  "x": 156.621,
  "y": -763.455,
  "z": -444.37,
  "temperature": 5276.86,
  "color": 16776144
},
{
  "ra": 161.461,
  "dec": -59.4887,
  "apparent_magnitude": 6.86502,
  "absolute_magnitude": -5.17672,
  "distance": 2560.64,
  "x": 2295.61,
  "y": 358.895,
  "z": -1076.23,
  "temperature": 3566.15,
  "color": 16738874
},
{
  "ra": 128.097,
  "dec": -49.6013,
  "apparent_magnitude": 5.47522,
  "absolute_magnitude": -4.28477,
  "distance": 895.363,
  "x": 783.808,
  "y": -338.992,
  "z": 269.079,
  "temperature": 17315.4,
  "color": 13230847
},
{
  "ra": 297.881,
  "dec": 19.1784,
  "apparent_magnitude": 6.66484,
  "absolute_magnitude": -2.27195,
  "distance": 612.854,
  "x": 461.11,
  "y": -342.09,
  "z": -214.34,
  "temperature": 3639.09,
  "color": 16738874
},
{
  "ra": 102.53,
  "dec": -5.81133,
  "apparent_magnitude": 6.67686,
  "absolute_magnitude": -3.67099,
  "distance": 1173.74,
  "x": 1165.95,
  "y": 134.851,
  "z": -5.88046,
  "temperature": 4732.53,
  "color": 16764015
},
{
  "ra": 272.678,
  "dec": 25.5203,
  "apparent_magnitude": 6.84701,
  "absolute_magnitude": -2.29238,
  "distance": 672.79,
  "x": 585.411,
  "y": -299.533,
  "z": -142.196,
  "temperature": 5320.06,
  "color": 16776144
},
{
  "ra": 339.027,
  "dec": -16.3881,
  "apparent_magnitude": 5.98603,
  "absolute_magnitude": -4.17183,
  "distance": 1075.4,
  "x": 597.018,
  "y": -862.587,
  "z": 236.657,
  "temperature": 23439.4,
  "color": 13230847
},
{
  "ra": 125.026,
  "dec": 2.7656,
  "apparent_magnitude": 6.11821,
  "absolute_magnitude": -3.19521,
  "distance": 728.927,
  "x": 622.482,
  "y": -332.964,
  "z": -181.619,
  "temperature": 4574.05,
  "color": 16764015
},
{
  "ra": 127.624,
  "dec": -36.7213,
  "apparent_magnitude": 5.66416,
  "absolute_magnitude": -5.33355,
  "distance": 1583.23,
  "x": 1442.3,
  "y": -390.248,
  "z": 523.532,
  "temperature": 3695.43,
  "color": 16738874
},
{
  "ra": 298.007,
  "dec": 24.9921,
  "apparent_magnitude": 4.73003,
  "absolute_magnitude": -5.60619,
  "distance": 1167.47,
  "x": 405.407,
  "y": -531.605,
  "z": -957.089,
  "temperature": 7592.41,
  "color": 16316415
},
{
  "ra": 109.668,
  "dec": -24.5587,
  "apparent_magnitude": 5.0917,
  "absolute_magnitude": -5.35229,
  "distance": 1226.87,
  "x": 824.823,
  "y": -901.72,
  "z": -108.494,
  "temperature": 23134,
  "color": 13230847
},
{
  "ra": 81.1192,
  "dec": -2.39715,
  "apparent_magnitude": 6.14559,
  "absolute_magnitude": -5.39368,
  "distance": 2031.67,
  "x": 1372.41,
  "y": -931.848,
  "z": -1172.97,
  "temperature": 18608.2,
  "color": 13230847
},
{
  "ra": 313.741,
  "dec": 33.764,
  "apparent_magnitude": 6.82385,
  "absolute_magnitude": -4.02166,
  "distance": 1476.05,
  "x": 1159.98,
  "y": -910.201,
  "z": -68.6834,
  "temperature": 3760,
  "color": 16764015
},
{
  "ra": 146.312,
  "dec": -62.5079,
  "apparent_magnitude": 6.35073,
  "absolute_magnitude": -5.04093,
  "distance": 1898.16,
  "x": 1658.9,
  "y": -714.776,
  "z": -583.227,
  "temperature": 5488.41,
  "color": 16776144
},
{
  "ra": 330.519,
  "dec": 58.0004,
  "apparent_magnitude": 6.89634,
  "absolute_magnitude": -4.73041,
  "distance": 2115.19,
  "x": 1662.53,
  "y": -1259.7,
  "z": 350.995,
  "temperature": 24865.8,
  "color": 13230847
},
{
  "ra": 275.454,
  "dec": -16.3246,
  "apparent_magnitude": 6.85775,
  "absolute_magnitude": -3.54105,
  "distance": 1201.6,
  "x": 1175.47,
  "y": -245.981,
  "z": 40.0125,
  "temperature": 5896.81,
  "color": 16776144
},
]
