[
{
  "ra": 339.115,
  "dec": 58.4261,
  "apparent_magnitude": 6.35933,
  "absolute_magnitude": -11.5547,
  "distance": 38266.1,
  "x": -5039.92,
  "y": 4597,
  "z": 37653.2,
  "temperature": 4871.35,
  "color": 16764015
},
{
  "ra": 273.804,
  "dec": -20.388,
  "apparent_magnitude": 5.64362,
  "absolute_magnitude": -10.0662,
  "distance": 13866.6,
  "x": 5312.15,
  "y": 2427.93,
  "z": -12576.6,
  "temperature": 21691.1,
  "color": 13230847
},
{
  "ra": 82.4277,
  "dec": 35.375,
  "apparent_magnitude": 5.89154,
  "absolute_magnitude": -8.7747,
  "distance": 8575.27,
  "x": -1440.29,
  "y": -3993.36,
  "z": -7450.77,
  "temperature": 29993.6,
  "color": 13230847
},
{
  "ra": 136.927,
  "dec": -44.6324,
  "apparent_magnitude": 6.83301,
  "absolute_magnitude": -8.55476,
  "distance": 11955.1,
  "x": 8430.31,
  "y": -7072.67,
  "z": -4672.51,
  "temperature": 7899.92,
  "color": 16316415
},
{
  "ra": 126.472,
  "dec": -33.5641,
  "apparent_magnitude": 6.89313,
  "absolute_magnitude": -6.14479,
  "distance": 4051.19,
  "x": 3701.34,
  "y": 511.228,
  "z": -1565.52,
  "temperature": 3645.77,
  "color": 16738874
},
{
  "ra": 333.289,
  "dec": 53.6239,
  "apparent_magnitude": 6.78401,
  "absolute_magnitude": -5.77864,
  "distance": 3254.84,
  "x": 1914.84,
  "y": 1555.39,
  "z": 2123.24,
  "temperature": 3685.42,
  "color": 16738874
},
{
  "ra": 339.115,
  "dec": 58.4261,
  "apparent_magnitude": 6.35933,
  "absolute_magnitude": -11.5547,
  "distance": 38266.1,
  "x": -5039.92,
  "y": 4597,
  "z": 37653.2,
  "temperature": 4871.35,
  "color": 16764015
},
{
  "ra": 273.804,
  "dec": -20.388,
  "apparent_magnitude": 5.64362,
  "absolute_magnitude": -10.0662,
  "distance": 13866.6,
  "x": 5312.15,
  "y": 2427.93,
  "z": -12576.6,
  "temperature": 21691.1,
  "color": 13230847
},
{
  "ra": 82.4277,
  "dec": 35.375,
  "apparent_magnitude": 5.89154,
  "absolute_magnitude": -8.7747,
  "distance": 8575.27,
  "x": -1440.29,
  "y": -3993.36,
  "z": -7450.77,
  "temperature": 29993.6,
  "color": 13230847
},
{
  "ra": 136.927,
  "dec": -44.6324,
  "apparent_magnitude": 6.83301,
  "absolute_magnitude": -8.55476,
  "distance": 11955.1,
  "x": 8430.31,
  "y": -7072.67,
  "z": -4672.51,
  "temperature": 7899.92,
  "color": 16316415
},
{
  "ra": 126.472,
  "dec": -33.5641,
  "apparent_magnitude": 6.89313,
  "absolute_magnitude": -6.14479,
  "distance": 4051.19,
  "x": 3701.34,
  "y": 511.228,
  "z": -1565.52,
  "temperature": 3645.77,
  "color": 16738874
},
{
  "ra": 333.289,
  "dec": 53.6239,
  "apparent_magnitude": 6.78401,
  "absolute_magnitude": -5.77864,
  "distance": 3254.84,
  "x": 1914.84,
  "y": 1555.39,
  "z": 2123.24,
  "temperature": 3685.42,
  "color": 16738874
},
]
