[
{
  "ra": 339.115,
  "dec": 58.4261,
  "apparent_magnitude": 6.00057,
  "absolute_magnitude": -11.5547,
  "distance": 32438.6,
  "x": -9671.35,
  "y": -3838.37,
  "z": 30724.5,
  "temperature": 4871.35,
  "color": 16764015
},
{
  "ra": 273.804,
  "dec": -20.388,
  "apparent_magnitude": 6.48412,
  "absolute_magnitude": -10.0662,
  "distance": 20420.8,
  "x": 680.721,
  "y": -6007.44,
  "z": -19505.2,
  "temperature": 21691.1,
  "color": 13230847
},
{
  "ra": 102.719,
  "dec": -0.0731912,
  "apparent_magnitude": 6.7776,
  "absolute_magnitude": -6.82735,
  "distance": 5260.05,
  "x": -2835.69,
  "y": -186.01,
  "z": -4426.33,
  "temperature": 3679.72,
  "color": 16738874
},
{
  "ra": 338.8,
  "dec": 14.6105,
  "apparent_magnitude": 6.81342,
  "absolute_magnitude": -6.61946,
  "distance": 4859.33,
  "x": -1253.11,
  "y": -4497.6,
  "z": 1346.97,
  "temperature": 5208.01,
  "color": 16776144
},
{
  "ra": 202.229,
  "dec": -62.1023,
  "apparent_magnitude": 6.83215,
  "absolute_magnitude": -6.41416,
  "distance": 4459.25,
  "x": 2083.66,
  "y": -3533.88,
  "z": -1747.85,
  "temperature": 8199.93,
  "color": 16316415
},
{
  "ra": 339.115,
  "dec": 58.4261,
  "apparent_magnitude": 6.00057,
  "absolute_magnitude": -11.5547,
  "distance": 32438.6,
  "x": -9671.35,
  "y": -3838.37,
  "z": 30724.5,
  "temperature": 4871.35,
  "color": 16764015
},
{
  "ra": 273.804,
  "dec": -20.388,
  "apparent_magnitude": 6.48412,
  "absolute_magnitude": -10.0662,
  "distance": 20420.8,
  "x": 680.721,
  "y": -6007.44,
  "z": -19505.2,
  "temperature": 21691.1,
  "color": 13230847
},
{
  "ra": 102.719,
  "dec": -0.0731912,
  "apparent_magnitude": 6.7776,
  "absolute_magnitude": -6.82735,
  "distance": 5260.05,
  "x": -2835.69,
  "y": -186.01,
  "z": -4426.33,
  "temperature": 3679.72,
  "color": 16738874
},
{
  "ra": 338.8,
  "dec": 14.6105,
  "apparent_magnitude": 6.81342,
  "absolute_magnitude": -6.61946,
  "distance": 4859.33,
  "x": -1253.11,
  "y": -4497.6,
  "z": 1346.97,
  "temperature": 5208.01,
  "color": 16776144
},
{
  "ra": 202.229,
  "dec": -62.1023,
  "apparent_magnitude": 6.83215,
  "absolute_magnitude": -6.41416,
  "distance": 4459.25,
  "x": 2083.66,
  "y": -3533.88,
  "z": -1747.85,
  "temperature": 8199.93,
  "color": 16316415
},
]
